aske/__init__.py
aske/cli.py
aske/core/__init__.py
aske-0.1.1.dist-info/LICENSE
aske-0.1.1.dist-info/METADATA
aske-0.1.1.dist-info/WHEEL
aske-0.1.1.dist-info/entry_points.txt
aske-0.1.1.dist-info/top_level.txt
aske-0.1.1.dist-info/RECORD
