Metadata-Version: 2.2
Name: aske
Version: 0.1.1
Summary: Platform Architect Development Framework
Author: ASKE Team
License: MIT License
Project-URL: Homepage, https://github.com/yourusername/aske
Keywords: platform,architecture,development,framework
Classifier: License :: OSI Approved :: MIT License
Classifier: Programming Language :: Python
Classifier: Programming Language :: Python :: 3
Requires-Python: >=3.8
License-File: LICENSE
Requires-Dist: click>=8.0.0
Requires-Dist: pyyaml>=6.0
Requires-Dist: python-dotenv>=1.0.0
Provides-Extra: dev
Requires-Dist: black; extra == "dev"
Requires-Dist: pytest; extra == "dev"
